AUTHORS
ChangeLog
LICENSE
MANIFEST.in
Makefile
README.rst
build_dist.sh
setup.cfg
setup.py
docs/Makefile
docs/conf.py
docs/index.rst
docs/make.bat
guidedlda/__init__.py
guidedlda/_guidedlda.c
guidedlda/_guidedlda.pyx
guidedlda/_setup_hooks.py
guidedlda/datasets.py
guidedlda/gamma.c
guidedlda/gamma.h
guidedlda/guidedlda.py
guidedlda/utils.py
guidedlda.egg-info/PKG-INFO
guidedlda.egg-info/SOURCES.txt
guidedlda.egg-info/dependency_links.txt
guidedlda.egg-info/not-zip-safe
guidedlda.egg-info/pbr.json
guidedlda.egg-info/top_level.txt
guidedlda/tests/__init__.py
guidedlda/tests/nyt.ldac
guidedlda/tests/nyt.titles
guidedlda/tests/nyt.tokens
guidedlda/tests/reuters.ldac
guidedlda/tests/reuters.titles
guidedlda/tests/reuters.tokens
guidedlda/tests/test_datasets.py
guidedlda/tests/test_guidedlda_nyt.py
guidedlda/tests/test_lda.py
guidedlda/tests/test_lda_reuters.py
guidedlda/tests/test_lda_sparse.py
guidedlda/tests/test_lda_transform.py
guidedlda/tests/test_utils.py